[
    {
        "id": "3379",
        "facilityid": "4583",
        "name": "Roma Street Railway Station",
        "suburb_list": "B, Brisbane City",
        "facilitytype": "Train station",
        "address1": "Roma Street",
        "town": "Brisbane City",
        "state": "QLD",
        "addressnote": null,
        "latitude": -27.46471353,
        "longitude": 153.01903908,
        "parking": "False",
        "parkingaccessible": "False",
        "parkingnote": null,
        "keyrequired": "False",
        "mlak24": "False",
        "mlakafterhours": "False",
        "paymentrequired": "False",
        "accessnote": null,
        "adultchange": "False",
        "changingplaces": "False",
        "byosling": "False",
        "acshower": "False",
        "acmlak": "False",
        "adultchangenote": null,
        "babychange": "True",
        "babycareroom": "False",
        "babychangenote": null,
        "dumppoint": "False",
        "dpwashout": "False",
        "dpafterhours": "False",
        "dumppointnote": null,
        "openinghours": "OPEN: 3:45am-10pm",
        "openinghoursnote": null,
        "male": "True",
        "female": "True",
        "unisex": "False",
        "allgender": "False",
        "ambulant": "False",
        "accessible": "True",
        "lhtransfer": "False",
        "rhtransfer": "False",
        "toiletnote": null,
        "sharpsdisposal": "False",
        "drinkingwater": "True",
        "sanitarydisposal": "False",
        "menspaddisposal": "False",
        "shower": "False",
        "rank": 0.057308756,
        "geopoint": {
            "lon": 153.01903908,
            "lat": -27.46471353
        },
        "url_open_data_map": "https://data.brisbane.qld.gov.au/explore/dataset/public-toilets-in-brisbane/map/?q=facilityid:[4583]",
        "url": "https://toiletmap.gov.au/facility/4583",
        "lga_name": "Brisbane",
        "lga_code": "31000"
    },
    {
        "id": "3380",
        "facilityid": "4584",
        "name": "Central Railway Station",
        "suburb_list": "B, Brisbane City",
        "facilitytype": "Train station",
        "address1": "Ann Street",
        "town": "Brisbane City",
        "state": "QLD",
        "addressnote": null,
        "latitude": -27.46610843,
        "longitude": 153.0259603,
        "parking": "False",
        "parkingaccessible": "False",
        "parkingnote": null,
        "keyrequired": "False",
        "mlak24": "False",
        "mlakafterhours": "False",
        "paymentrequired": "False",
        "accessnote": null,
        "adultchange": "False",
        "changingplaces": "False",
        "byosling": "False",
        "acshower": "False",
        "acmlak": "False",
        "adultchangenote": null,
        "babychange": "True",
        "babycareroom": "False",
        "babychangenote": null,
        "dumppoint": "False",
        "dpwashout": "False",
        "dpafterhours": "False",
        "dumppointnote": null,
        "openinghours": "OPEN: Fri 3:45am-2am, Sat 3:35am-2am, Mon-Thu 3:45am-1am, Sun 3:30am-12:15am",
        "openinghoursnote": null,
        "male": "True",
        "female": "True",
        "unisex": "False",
        "allgender": "False",
        "ambulant": "False",
        "accessible": "True",
        "lhtransfer": "False",
        "rhtransfer": "False",
        "toiletnote": null,
        "sharpsdisposal": "False",
        "drinkingwater": "True",
        "sanitarydisposal": "False",
        "menspaddisposal": "False",
        "shower": "False",
        "rank": 0.057308756,
        "geopoint": {
            "lon": 153.0259603,
            "lat": -27.46610843
        },
        "url_open_data_map": "https://data.brisbane.qld.gov.au/explore/dataset/public-toilets-in-brisbane/map/?q=facilityid:[4584]",
        "url": "https://toiletmap.gov.au/facility/4584",
        "lga_name": "Brisbane",
        "lga_code": "31000"
    },
    {
        "id": "9085",
        "facilityid": "16091",
        "name": "Cathedral Square",
        "suburb_list": "B, Brisbane City",
        "facilitytype": "Park or reserve",
        "address1": "Turbot Street",
        "town": "Brisbane City",
        "state": "QLD",
        "addressnote": null,
        "latitude": -27.46351738,
        "longitude": 153.02854814,
        "parking": "False",
        "parkingaccessible": "False",
        "parkingnote": null,
        "keyrequired": "False",
        "mlak24": "False",
        "mlakafterhours": "False",
        "paymentrequired": "False",
        "accessnote": null,
        "adultchange": "False",
        "changingplaces": "False",
        "byosling": "False",
        "acshower": "False",
        "acmlak": "False",
        "adultchangenote": null,
        "babychange": "False",
        "babycareroom": "False",
        "babychangenote": null,
        "dumppoint": "False",
        "dpwashout": "False",
        "dpafterhours": "False",
        "dumppointnote": null,
        "openinghours": "OPEN: 6am-8pm",
        "openinghoursnote": null,
        "male": "False",
        "female": "False",
        "unisex": "True",
        "allgender": "False",
        "ambulant": "False",
        "accessible": "True",
        "lhtransfer": "False",
        "rhtransfer": "False",
        "toiletnote": "New Toilet was constructed in 2017",
        "sharpsdisposal": "False",
        "drinkingwater": "False",
        "sanitarydisposal": "False",
        "menspaddisposal": "False",
        "shower": "False",
        "rank": 0.057308756,
        "geopoint": {
            "lon": 153.02854814,
            "lat": -27.46351738
        },
        "url_open_data_map": "https://data.brisbane.qld.gov.au/explore/dataset/public-toilets-in-brisbane/map/?q=facilityid:[16091]",
        "url": "https://toiletmap.gov.au/facility/16091",
        "lga_name": "Brisbane",
        "lga_code": "31000"
    },
    {
        "id": "9156",
        "facilityid": "16204",
        "name": "City Botanic Gardens 2",
        "suburb_list": "B, Brisbane City",
        "facilitytype": "Park or reserve",
        "address1": "Gardens Point Road",
        "town": "Brisbane City",
        "state": "QLD",
        "addressnote": null,
        "latitude": -27.47793318,
        "longitude": 153.03020941,
        "parking": "True",
        "parkingaccessible": "True",
        "parkingnote": null,
        "keyrequired": "False",
        "mlak24": "False",
        "mlakafterhours": "False",
        "paymentrequired": "False",
        "accessnote": null,
        "adultchange": "False",
        "changingplaces": "False",
        "byosling": "False",
        "acshower": "False",
        "acmlak": "False",
        "adultchangenote": null,
        "babychange": "False",
        "babycareroom": "False",
        "babychangenote": null,
        "dumppoint": "False",
        "dpwashout": "False",
        "dpafterhours": "False",
        "dumppointnote": null,
        "openinghours": "OPEN: Daylight hours",
        "openinghoursnote": "Park is also closed after daylight hours",
        "male": "True",
        "female": "True",
        "unisex": "False",
        "allgender": "False",
        "ambulant": "False",
        "accessible": "True",
        "lhtransfer": "False",
        "rhtransfer": "False",
        "toiletnote": "Toilet is being refurbished in 2012",
        "sharpsdisposal": "False",
        "drinkingwater": "True",
        "sanitarydisposal": "False",
        "menspaddisposal": "False",
        "shower": "False",
        "rank": 0.057308756,
        "geopoint": {
            "lon": 153.03020941,
            "lat": -27.47793318
        },
        "url_open_data_map": "https://data.brisbane.qld.gov.au/explore/dataset/public-toilets-in-brisbane/map/?q=facilityid:[16204]",
        "url": "https://toiletmap.gov.au/facility/16204",
        "lga_name": "Brisbane",
        "lga_code": "31000"
    },
    {
        "id": "9674",
        "facilityid": "17311",
        "name": "Alice Street Information Booth",
        "suburb_list": "B, Brisbane City",
        "facilitytype": "Park or reserve",
        "address1": "Alice Street",
        "town": "Brisbane City",
        "state": "QLD",
        "addressnote": null,
        "latitude": -27.47444052,
        "longitude": 153.02989271,
        "parking": "True",
        "parkingaccessible": "False",
        "parkingnote": null,
        "keyrequired": "False",
        "mlak24": "False",
        "mlakafterhours": "True",
        "paymentrequired": "False",
        "accessnote": "Council has installed Accessible Adult Changing Facilities (AACFs) to enable adults with severe disabilities and their carers to visit the place.\nMLAK required: Yes",
        "adultchange": "True",
        "changingplaces": "True",
        "byosling": "True",
        "acshower": "False",
        "acmlak": "False",
        "adultchangenote": null,
        "babychange": "False",
        "babycareroom": "False",
        "babychangenote": null,
        "dumppoint": "False",
        "dpwashout": "False",
        "dpafterhours": "False",
        "dumppointnote": null,
        "openinghours": "OPEN: Daylight hours",
        "openinghoursnote": "Park is also closed after daylight hours",
        "male": "True",
        "female": "True",
        "unisex": "False",
        "allgender": "False",
        "ambulant": "False",
        "accessible": "True",
        "lhtransfer": "True",
        "rhtransfer": "True",
        "toiletnote": "Toilet is located beneath the Information Booth in the centre of the gardens. Adult assistance could be required to negotiate entrance ramp. Toilet was refurbished in 2009",
        "sharpsdisposal": "True",
        "drinkingwater": "False",
        "sanitarydisposal": "True",
        "menspaddisposal": "False",
        "shower": "False",
        "rank": 0.057308756,
        "geopoint": {
            "lon": 153.02989271,
            "lat": -27.47444052
        },
        "url_open_data_map": "https://data.brisbane.qld.gov.au/explore/dataset/public-toilets-in-brisbane/map/?q=facilityid:[17311]",
        "url": "https://toiletmap.gov.au/facility/17311",
        "lga_name": "Brisbane",
        "lga_code": "31000"
    },
    {
        "id": "10221",
        "facilityid": "18007",
        "name": "Uptown",
        "suburb_list": "B, Brisbane City",
        "facilitytype": "Shopping centre",
        "address1": "91 Queen Street",
        "town": "Brisbane City",
        "state": "QLD",
        "addressnote": null,
        "latitude": -27.470141,
        "longitude": 153.024554,
        "parking": "True",
        "parkingaccessible": "True",
        "parkingnote": null,
        "keyrequired": "False",
        "mlak24": "False",
        "mlakafterhours": "False",
        "paymentrequired": "False",
        "accessnote": null,
        "adultchange": "False",
        "changingplaces": "False",
        "byosling": "False",
        "acshower": "False",
        "acmlak": "False",
        "adultchangenote": null,
        "babychange": "True",
        "babycareroom": "False",
        "babychangenote": null,
        "dumppoint": "False",
        "dpwashout": "False",
        "dpafterhours": "False",
        "dumppointnote": null,
        "openinghours": "OPEN: Mon-Thu 9am-5:30pm, Fri 9am-9pm, Sat 9am-5pm, Sun 10am-5pm",
        "openinghoursnote": "Closed Good Friday, Christmas Day. Shopping Centre open on other public holidays as gazetted",
        "male": "True",
        "female": "True",
        "unisex": "False",
        "allgender": "False",
        "ambulant": "False",
        "accessible": "True",
        "lhtransfer": "False",
        "rhtransfer": "False",
        "toiletnote": "Parenting room located on lvl 2.",
        "sharpsdisposal": "True",
        "drinkingwater": "False",
        "sanitarydisposal": "True",
        "menspaddisposal": "False",
        "shower": "False",
        "rank": 0.057308756,
        "geopoint": {
            "lon": 153.024554,
            "lat": -27.470141
        },
        "url_open_data_map": "https://data.brisbane.qld.gov.au/explore/dataset/public-toilets-in-brisbane/map/?q=facilityid:[18007]",
        "url": "https://toiletmap.gov.au/facility/18007",
        "lga_name": "Brisbane",
        "lga_code": "31000"
    },
    {
        "id": "10238",
        "facilityid": "18035",
        "name": "Post Office Square",
        "suburb_list": "B, Brisbane City",
        "facilitytype": "Shopping centre",
        "address1": "270 Queen Street",
        "town": "Brisbane City",
        "state": "QLD",
        "addressnote": null,
        "latitude": -27.4665994,
        "longitude": 153.0286915,
        "parking": "True",
        "parkingaccessible": "False",
        "parkingnote": "24/hr paid car park access to Secure Parking, Post Office Square. Car entry/exit via Adelaide Street. Lift access into the Post Office Square Shopping Centre during open hours.",
        "keyrequired": "False",
        "mlak24": "False",
        "mlakafterhours": "False",
        "paymentrequired": "True",
        "accessnote": "Book online or pay at the machines in the car park.\nDisability car parks not available at this car park, however lift access into Post Office Square available during centre open hours.",
        "adultchange": "False",
        "changingplaces": "False",
        "byosling": "False",
        "acshower": "False",
        "acmlak": "False",
        "adultchangenote": null,
        "babychange": "True",
        "babycareroom": "False",
        "babychangenote": "Baby change station in PWD.",
        "dumppoint": "False",
        "dpwashout": "False",
        "dpafterhours": "False",
        "dumppointnote": null,
        "openinghours": "OPEN: Mon-Fri 6:30am-5pm, Sat 9am-3pm",
        "openinghoursnote": "Selected stores opened on the weekend.  Please confirm weekend trading hours directly with stores.\n\nClosed on public holidays.",
        "male": "True",
        "female": "True",
        "unisex": "True",
        "allgender": "False",
        "ambulant": "True",
        "accessible": "True",
        "lhtransfer": "False",
        "rhtransfer": "False",
        "toiletnote": "Unisex, Ambulance and Accessible Bathroom available as PWD. \nBaby change station & sharp disposals in PWD.",
        "sharpsdisposal": "True",
        "drinkingwater": "False",
        "sanitarydisposal": "True",
        "menspaddisposal": "False",
        "shower": "False",
        "rank": 0.057308756,
        "geopoint": {
            "lon": 153.0286915,
            "lat": -27.4665994
        },
        "url_open_data_map": "https://data.brisbane.qld.gov.au/explore/dataset/public-toilets-in-brisbane/map/?q=facilityid:[18035]",
        "url": "https://toiletmap.gov.au/facility/18035",
        "lga_name": "Brisbane",
        "lga_code": "31000"
    },
    {
        "id": "10300",
        "facilityid": "18107",
        "name": "Wintergarden",
        "suburb_list": "B, Brisbane City",
        "facilitytype": "Shopping centre",
        "address1": "162 Elizabeth Street",
        "town": "Brisbane City",
        "state": "QLD",
        "addressnote": null,
        "latitude": -27.46930222,
        "longitude": 153.02640333,
        "parking": "True",
        "parkingaccessible": "True",
        "parkingnote": null,
        "keyrequired": "False",
        "mlak24": "False",
        "mlakafterhours": "False",
        "paymentrequired": "False",
        "accessnote": null,
        "adultchange": "False",
        "changingplaces": "False",
        "byosling": "False",
        "acshower": "False",
        "acmlak": "False",
        "adultchangenote": null,
        "babychange": "True",
        "babycareroom": "False",
        "babychangenote": null,
        "dumppoint": "False",
        "dpwashout": "False",
        "dpafterhours": "False",
        "dumppointnote": null,
        "openinghours": "OPEN: Mon-Thu 9am-5:30pm, Fri 9am-9pm, Sat 9am-5pm, Sun 10:30am-4pm",
        "openinghoursnote": "Open 10:30am-4pm on public holidays.",
        "male": "True",
        "female": "True",
        "unisex": "False",
        "allgender": "False",
        "ambulant": "False",
        "accessible": "True",
        "lhtransfer": "False",
        "rhtransfer": "False",
        "toiletnote": "Parenting rooms are located on level 1 and level 3.",
        "sharpsdisposal": "False",
        "drinkingwater": "False",
        "sanitarydisposal": "True",
        "menspaddisposal": "False",
        "shower": "False",
        "rank": 0.057308756,
        "geopoint": {
            "lon": 153.02640333,
            "lat": -27.46930222
        },
        "url_open_data_map": "https://data.brisbane.qld.gov.au/explore/dataset/public-toilets-in-brisbane/map/?q=facilityid:[18107]",
        "url": "https://toiletmap.gov.au/facility/18107",
        "lga_name": "Brisbane",
        "lga_code": "31000"
    },
    {
        "id": "10814",
        "facilityid": "18767",
        "name": "Albert Street",
        "suburb_list": "B, Brisbane City",
        "facilitytype": "Shopping centre",
        "address1": "Albert Street",
        "town": "Brisbane City",
        "state": "QLD",
        "addressnote": null,
        "latitude": -27.46976516,
        "longitude": 153.0253948,
        "parking": "False",
        "parkingaccessible": "False",
        "parkingnote": null,
        "keyrequired": "False",
        "mlak24": "False",
        "mlakafterhours": "False",
        "paymentrequired": "False",
        "accessnote": null,
        "adultchange": "False",
        "changingplaces": "False",
        "byosling": "False",
        "acshower": "False",
        "acmlak": "False",
        "adultchangenote": null,
        "babychange": "True",
        "babycareroom": "False",
        "babychangenote": null,
        "dumppoint": "False",
        "dpwashout": "False",
        "dpafterhours": "False",
        "dumppointnote": null,
        "openinghours": "OPEN: 24 hours",
        "openinghoursnote": null,
        "male": "True",
        "female": "True",
        "unisex": "False",
        "allgender": "False",
        "ambulant": "False",
        "accessible": "True",
        "lhtransfer": "False",
        "rhtransfer": "False",
        "toiletnote": "Toilet is located beneath the street near the Queen Street Mall Toilet was refurbished in 2006",
        "sharpsdisposal": "True",
        "drinkingwater": "False",
        "sanitarydisposal": "True",
        "menspaddisposal": "False",
        "shower": "False",
        "rank": 0.057308756,
        "geopoint": {
            "lon": 153.0253948,
            "lat": -27.46976516
        },
        "url_open_data_map": "https://data.brisbane.qld.gov.au/explore/dataset/public-toilets-in-brisbane/map/?q=facilityid:[18767]",
        "url": "https://toiletmap.gov.au/facility/18767",
        "lga_name": "Brisbane",
        "lga_code": "31000"
    },
    {
        "id": "13157",
        "facilityid": "39357",
        "name": "Queens Plaza",
        "suburb_list": "B, Brisbane City",
        "facilitytype": "Shopping centre",
        "address1": "226 Queen Street",
        "town": "Brisbane City",
        "state": "QLD",
        "addressnote": null,
        "latitude": -27.46874,
        "longitude": 153.02639,
        "parking": "True",
        "parkingaccessible": "True",
        "parkingnote": null,
        "keyrequired": "False",
        "mlak24": "False",
        "mlakafterhours": "False",
        "paymentrequired": "False",
        "accessnote": null,
        "adultchange": "False",
        "changingplaces": "False",
        "byosling": "False",
        "acshower": "False",
        "acmlak": "False",
        "adultchangenote": null,
        "babychange": "True",
        "babycareroom": "False",
        "babychangenote": null,
        "dumppoint": "False",
        "dpwashout": "False",
        "dpafterhours": "False",
        "dumppointnote": null,
        "openinghours": "OPEN: Fri 9am-9pm, Mon-Thu 9am-5:30pm, Sun 10:30am-4pm, Sat 9am-5pm",
        "openinghoursnote": null,
        "male": "True",
        "female": "True",
        "unisex": "True",
        "allgender": "False",
        "ambulant": "True",
        "accessible": "True",
        "lhtransfer": "False",
        "rhtransfer": "False",
        "toiletnote": null,
        "sharpsdisposal": "False",
        "drinkingwater": "False",
        "sanitarydisposal": "True",
        "menspaddisposal": "False",
        "shower": "False",
        "rank": 0.057308756,
        "geopoint": {
            "lon": 153.02639,
            "lat": -27.46874
        },
        "url_open_data_map": "https://data.brisbane.qld.gov.au/explore/dataset/public-toilets-in-brisbane/map/?q=facilityid:[39357]",
        "url": "https://toiletmap.gov.au/facility/39357",
        "lga_name": "Brisbane",
        "lga_code": "31000"
    },
    {
        "id": "13158",
        "facilityid": "39359",
        "name": "QueensPlaza",
        "suburb_list": "B, Brisbane City",
        "facilitytype": "Shopping centre",
        "address1": "226 Queen Street",
        "town": "Brisbane City",
        "state": "QLD",
        "addressnote": null,
        "latitude": -27.46837787,
        "longitude": 153.02652588,
        "parking": "True",
        "parkingaccessible": "True",
        "parkingnote": null,
        "keyrequired": "False",
        "mlak24": "False",
        "mlakafterhours": "False",
        "paymentrequired": "False",
        "accessnote": null,
        "adultchange": "False",
        "changingplaces": "False",
        "byosling": "False",
        "acshower": "False",
        "acmlak": "False",
        "adultchangenote": null,
        "babychange": "True",
        "babycareroom": "False",
        "babychangenote": null,
        "dumppoint": "False",
        "dpwashout": "False",
        "dpafterhours": "False",
        "dumppointnote": null,
        "openinghours": "OPEN: Fri 9am-9pm, Mon-Thu 9am-5:30pm, Sat 9am-5pm, Sun 10:30am-4pm",
        "openinghoursnote": null,
        "male": "True",
        "female": "True",
        "unisex": "True",
        "allgender": "False",
        "ambulant": "True",
        "accessible": "True",
        "lhtransfer": "False",
        "rhtransfer": "False",
        "toiletnote": null,
        "sharpsdisposal": "False",
        "drinkingwater": "False",
        "sanitarydisposal": "True",
        "menspaddisposal": "False",
        "shower": "False",
        "rank": 0.057308756,
        "geopoint": {
            "lon": 153.02652588,
            "lat": -27.46837787
        },
        "url_open_data_map": "https://data.brisbane.qld.gov.au/explore/dataset/public-toilets-in-brisbane/map/?q=facilityid:[39359]",
        "url": "https://toiletmap.gov.au/facility/39359",
        "lga_name": "Brisbane",
        "lga_code": "31000"
    },
    {
        "id": "13989",
        "facilityid": "41817",
        "name": "Roma St Parklands (Administration)",
        "suburb_list": "B, Brisbane City",
        "facilitytype": "Other",
        "address1": "1 Parkland Boulevard",
        "town": "Brisbane City",
        "state": "QLD",
        "addressnote": null,
        "latitude": -27.46433491,
        "longitude": 153.01962392,
        "parking": "False",
        "parkingaccessible": "False",
        "parkingnote": null,
        "keyrequired": "False",
        "mlak24": "False",
        "mlakafterhours": "False",
        "paymentrequired": "False",
        "accessnote": null,
        "adultchange": "False",
        "changingplaces": "False",
        "byosling": "False",
        "acshower": "False",
        "acmlak": "False",
        "adultchangenote": null,
        "babychange": "True",
        "babycareroom": "False",
        "babychangenote": null,
        "dumppoint": "False",
        "dpwashout": "False",
        "dpafterhours": "False",
        "dumppointnote": null,
        "openinghours": "OPEN: Daylight hours",
        "openinghoursnote": null,
        "male": "False",
        "female": "False",
        "unisex": "True",
        "allgender": "False",
        "ambulant": "False",
        "accessible": "True",
        "lhtransfer": "False",
        "rhtransfer": "False",
        "toiletnote": null,
        "sharpsdisposal": "False",
        "drinkingwater": "False",
        "sanitarydisposal": "False",
        "menspaddisposal": "False",
        "shower": "False",
        "rank": 0.057308756,
        "geopoint": {
            "lon": 153.01962392,
            "lat": -27.46433491
        },
        "url_open_data_map": "https://data.brisbane.qld.gov.au/explore/dataset/public-toilets-in-brisbane/map/?q=facilityid:[41817]",
        "url": "https://toiletmap.gov.au/facility/41817",
        "lga_name": "Brisbane",
        "lga_code": "31000"
    },
    {
        "id": "17355",
        "facilityid": "54119",
        "name": "Brisbane City Hall",
        "suburb_list": "B, Brisbane City",
        "facilitytype": "Other",
        "address1": "87C Roma Street",
        "town": "Brisbane City",
        "state": "QLD",
        "addressnote": null,
        "latitude": -27.46895071,
        "longitude": 153.02350614,
        "parking": "False",
        "parkingaccessible": "False",
        "parkingnote": null,
        "keyrequired": "False",
        "mlak24": "True",
        "mlakafterhours": "False",
        "paymentrequired": "False",
        "accessnote": "Council has installed Accessible Adult Changing Facilities (AACFs) to enable adults with severe disabilities and their carers to visit the place.\nMLAK required: Yes\nAccess can also be requested via the City Hall concierge desk.",
        "adultchange": "True",
        "changingplaces": "False",
        "byosling": "True",
        "acshower": "False",
        "acmlak": "False",
        "adultchangenote": null,
        "babychange": "True",
        "babycareroom": "False",
        "babychangenote": null,
        "dumppoint": "False",
        "dpwashout": "False",
        "dpafterhours": "False",
        "dumppointnote": null,
        "openinghours": "OPEN: Daylight hours",
        "openinghoursnote": null,
        "male": "False",
        "female": "False",
        "unisex": "True",
        "allgender": "False",
        "ambulant": "False",
        "accessible": "True",
        "lhtransfer": "True",
        "rhtransfer": "False",
        "toiletnote": null,
        "sharpsdisposal": "False",
        "drinkingwater": "False",
        "sanitarydisposal": "True",
        "menspaddisposal": "False",
        "shower": "False",
        "rank": 0.057308756,
        "geopoint": {
            "lon": 153.02350614,
            "lat": -27.46895071
        },
        "url_open_data_map": "https://data.brisbane.qld.gov.au/explore/dataset/public-toilets-in-brisbane/map/?q=facilityid:[54119]",
        "url": "https://toiletmap.gov.au/facility/54119",
        "lga_name": "Brisbane",
        "lga_code": "31000"
    },
    {
        "id": "18383",
        "facilityid": "56414",
        "name": "Northey Street City Farm",
        "suburb_list": "W, Windsor (Qld)",
        "facilitytype": "Community building",
        "address1": "16 Victoria Street",
        "town": "Windsor (Qld)",
        "state": "QLD",
        "addressnote": "Freestanding unisex toilet building amongst Northey St City Farm",
        "latitude": -27.44252668,
        "longitude": 153.02806631,
        "parking": "True",
        "parkingaccessible": "False",
        "parkingnote": null,
        "keyrequired": "False",
        "mlak24": "False",
        "mlakafterhours": "False",
        "paymentrequired": "False",
        "accessnote": null,
        "adultchange": "False",
        "changingplaces": "False",
        "byosling": "False",
        "acshower": "False",
        "acmlak": "False",
        "adultchangenote": null,
        "babychange": "False",
        "babycareroom": "False",
        "babychangenote": null,
        "dumppoint": "False",
        "dpwashout": "False",
        "dpafterhours": "False",
        "dumppointnote": null,
        "openinghours": "OPEN: Daylight hours",
        "openinghoursnote": null,
        "male": "False",
        "female": "False",
        "unisex": "True",
        "allgender": "False",
        "ambulant": "False",
        "accessible": "True",
        "lhtransfer": "True",
        "rhtransfer": "False",
        "toiletnote": null,
        "sharpsdisposal": "True",
        "drinkingwater": "False",
        "sanitarydisposal": "True",
        "menspaddisposal": "False",
        "shower": "True",
        "rank": 0.057308756,
        "geopoint": {
            "lon": 153.02806631,
            "lat": -27.44252668
        },
        "url_open_data_map": "https://data.brisbane.qld.gov.au/explore/dataset/public-toilets-in-brisbane/map/?q=facilityid:[56414]",
        "url": "https://toiletmap.gov.au/facility/56414",
        "lga_name": "Brisbane",
        "lga_code": "31000"
    },
    {
        "id": "18885",
        "facilityid": "57183",
        "name": "Roma Street Parklands",
        "suburb_list": "B, Brisbane City",
        "facilitytype": "Park or reserve",
        "address1": "485 Wickham Terrace",
        "town": "Brisbane City",
        "state": "QLD",
        "addressnote": null,
        "latitude": -27.46215794,
        "longitude": 153.02049506,
        "parking": "False",
        "parkingaccessible": "False",
        "parkingnote": null,
        "keyrequired": "False",
        "mlak24": "False",
        "mlakafterhours": "False",
        "paymentrequired": "False",
        "accessnote": null,
        "adultchange": "False",
        "changingplaces": "False",
        "byosling": "False",
        "acshower": "False",
        "acmlak": "False",
        "adultchangenote": null,
        "babychange": "False",
        "babycareroom": "False",
        "babychangenote": null,
        "dumppoint": "False",
        "dpwashout": "False",
        "dpafterhours": "False",
        "dumppointnote": null,
        "openinghours": "OPEN: Daylight hours",
        "openinghoursnote": null,
        "male": "True",
        "female": "True",
        "unisex": "False",
        "allgender": "False",
        "ambulant": "False",
        "accessible": "True",
        "lhtransfer": "False",
        "rhtransfer": "False",
        "toiletnote": null,
        "sharpsdisposal": "False",
        "drinkingwater": "False",
        "sanitarydisposal": "False",
        "menspaddisposal": "False",
        "shower": "False",
        "rank": 0.057308756,
        "geopoint": {
            "lon": 153.02049506,
            "lat": -27.46215794
        },
        "url_open_data_map": "https://data.brisbane.qld.gov.au/explore/dataset/public-toilets-in-brisbane/map/?q=facilityid:[57183]",
        "url": "https://toiletmap.gov.au/facility/57183",
        "lga_name": "Brisbane",
        "lga_code": "31000"
    },
    {
        "id": "20421",
        "facilityid": "59352",
        "name": "Macarthur Central",
        "suburb_list": "B, Brisbane City",
        "facilitytype": "Shopping centre",
        "address1": "259 Queen Street",
        "town": "Brisbane City",
        "state": "QLD",
        "addressnote": null,
        "latitude": -27.46801952,
        "longitude": 153.02756676,
        "parking": "False",
        "parkingaccessible": "False",
        "parkingnote": null,
        "keyrequired": "False",
        "mlak24": "False",
        "mlakafterhours": "False",
        "paymentrequired": "False",
        "accessnote": null,
        "adultchange": "False",
        "changingplaces": "False",
        "byosling": "False",
        "acshower": "False",
        "acmlak": "False",
        "adultchangenote": null,
        "babychange": "True",
        "babycareroom": "False",
        "babychangenote": null,
        "dumppoint": "False",
        "dpwashout": "False",
        "dpafterhours": "False",
        "dumppointnote": null,
        "openinghours": "OPEN: Mon-Sat 7am-9pm, Sun 9am-6pm",
        "openinghoursnote": null,
        "male": "True",
        "female": "True",
        "unisex": "False",
        "allgender": "False",
        "ambulant": "False",
        "accessible": "True",
        "lhtransfer": "False",
        "rhtransfer": "False",
        "toiletnote": "There are toilets on both Level 1 and on the Lower Ground level. Accessible facilities are located on Level 1, near the lifts. Baby change facility is located on the Lower Ground level.",
        "sharpsdisposal": "False",
        "drinkingwater": "False",
        "sanitarydisposal": "True",
        "menspaddisposal": "False",
        "shower": "False",
        "rank": 0.057308756,
        "geopoint": {
            "lon": 153.02756676,
            "lat": -27.46801952
        },
        "url_open_data_map": "https://data.brisbane.qld.gov.au/explore/dataset/public-toilets-in-brisbane/map/?q=facilityid:[59352]",
        "url": "https://toiletmap.gov.au/facility/59352",
        "lga_name": "Brisbane",
        "lga_code": "31000"
    },
    {
        "id": "20422",
        "facilityid": "59353",
        "name": "Eagle Street Pier",
        "suburb_list": "B, Brisbane City",
        "facilitytype": "Other",
        "address1": "45 Eagle Street",
        "town": "Brisbane City",
        "state": "QLD",
        "addressnote": null,
        "latitude": -27.46901537,
        "longitude": 153.03045471,
        "parking": "False",
        "parkingaccessible": "False",
        "parkingnote": null,
        "keyrequired": "False",
        "mlak24": "False",
        "mlakafterhours": "False",
        "paymentrequired": "False",
        "accessnote": null,
        "adultchange": "False",
        "changingplaces": "False",
        "byosling": "False",
        "acshower": "False",
        "acmlak": "False",
        "adultchangenote": null,
        "babychange": "True",
        "babycareroom": "False",
        "babychangenote": null,
        "dumppoint": "False",
        "dpwashout": "False",
        "dpafterhours": "False",
        "dumppointnote": null,
        "openinghours": "OPEN: 10am-11pm",
        "openinghoursnote": null,
        "male": "True",
        "female": "True",
        "unisex": "False",
        "allgender": "False",
        "ambulant": "False",
        "accessible": "True",
        "lhtransfer": "False",
        "rhtransfer": "False",
        "toiletnote": "Toilets are located inside the entrance between Il Centro and City Winery, opposite Eat Sushi.",
        "sharpsdisposal": "False",
        "drinkingwater": "False",
        "sanitarydisposal": "True",
        "menspaddisposal": "False",
        "shower": "False",
        "rank": 0.057308756,
        "geopoint": {
            "lon": 153.03045471,
            "lat": -27.46901537
        },
        "url_open_data_map": "https://data.brisbane.qld.gov.au/explore/dataset/public-toilets-in-brisbane/map/?q=facilityid:[59353]",
        "url": "https://toiletmap.gov.au/facility/59353",
        "lga_name": "Brisbane",
        "lga_code": "31000"
    },
    {
        "id": "21374",
        "facilityid": "60825",
        "name": "Cathedral House at Penola Place",
        "suburb_list": "B, Brisbane City",
        "facilitytype": "Community building",
        "address1": "229 Elizabeth Street",
        "town": "Brisbane City",
        "state": "QLD",
        "addressnote": null,
        "latitude": -27.4689933,
        "longitude": 153.0283252,
        "parking": "False",
        "parkingaccessible": "False",
        "parkingnote": null,
        "keyrequired": "False",
        "mlak24": "False",
        "mlakafterhours": "False",
        "paymentrequired": "False",
        "accessnote": null,
        "adultchange": "False",
        "changingplaces": "False",
        "byosling": "False",
        "acshower": "False",
        "acmlak": "False",
        "adultchangenote": null,
        "babychange": "False",
        "babycareroom": "False",
        "babychangenote": null,
        "dumppoint": "False",
        "dpwashout": "False",
        "dpafterhours": "False",
        "dumppointnote": null,
        "openinghours": "OPEN: Daylight hours",
        "openinghoursnote": null,
        "male": "True",
        "female": "True",
        "unisex": "False",
        "allgender": "False",
        "ambulant": "False",
        "accessible": "False",
        "lhtransfer": "False",
        "rhtransfer": "False",
        "toiletnote": null,
        "sharpsdisposal": "False",
        "drinkingwater": "False",
        "sanitarydisposal": "False",
        "menspaddisposal": "False",
        "shower": "False",
        "rank": 0.057308756,
        "geopoint": {
            "lon": 153.0283252,
            "lat": -27.4689933
        },
        "url_open_data_map": "https://data.brisbane.qld.gov.au/explore/dataset/public-toilets-in-brisbane/map/?q=facilityid:[60825]",
        "url": "https://toiletmap.gov.au/facility/60825",
        "lga_name": "Brisbane",
        "lga_code": "31000"
    },
    {
        "id": "23388",
        "facilityid": "63313",
        "name": "175 Eagle Street",
        "suburb_list": "B, Brisbane City",
        "facilitytype": "Car park",
        "address1": "175 Eagle St",
        "town": "Brisbane City",
        "state": "QLD",
        "addressnote": null,
        "latitude": -27.4658152,
        "longitude": 153.0309422,
        "parking": "False",
        "parkingaccessible": "False",
        "parkingnote": null,
        "keyrequired": "False",
        "mlak24": "False",
        "mlakafterhours": "False",
        "paymentrequired": "False",
        "accessnote": null,
        "adultchange": "False",
        "changingplaces": "False",
        "byosling": "False",
        "acshower": "False",
        "acmlak": "False",
        "adultchangenote": null,
        "babychange": "False",
        "babycareroom": "False",
        "babychangenote": null,
        "dumppoint": "False",
        "dpwashout": "False",
        "dpafterhours": "False",
        "dumppointnote": null,
        "openinghours": "OPEN: Variable hours",
        "openinghoursnote": null,
        "male": "True",
        "female": "True",
        "unisex": "False",
        "allgender": "False",
        "ambulant": "False",
        "accessible": "True",
        "lhtransfer": "False",
        "rhtransfer": "False",
        "toiletnote": "The toilet is located upstairs from Riverside or downstairs from Eagle Street on walkway between the river and Eagle Street.",
        "sharpsdisposal": "False",
        "drinkingwater": "False",
        "sanitarydisposal": "False",
        "menspaddisposal": "False",
        "shower": "False",
        "rank": 0.057308756,
        "geopoint": {
            "lon": 153.0309422,
            "lat": -27.4658152
        },
        "url_open_data_map": "https://data.brisbane.qld.gov.au/explore/dataset/public-toilets-in-brisbane/map/?q=facilityid:[63313]",
        "url": "https://toiletmap.gov.au/facility/63313",
        "lga_name": "Brisbane",
        "lga_code": "31000"
    },
    {
        "id": "24884",
        "facilityid": "65239",
        "name": "Roma Street Parkland Amphitheatre",
        "suburb_list": "B, Brisbane City",
        "facilitytype": "Other",
        "address1": "1 Parkland Boulevard",
        "town": "Brisbane City",
        "state": "QLD",
        "addressnote": "Located adjacent to the Amphitheatre.",
        "latitude": -27.46262703,
        "longitude": 153.02014502,
        "parking": "False",
        "parkingaccessible": "False",
        "parkingnote": null,
        "keyrequired": "False",
        "mlak24": "False",
        "mlakafterhours": "False",
        "paymentrequired": "False",
        "accessnote": null,
        "adultchange": "False",
        "changingplaces": "False",
        "byosling": "False",
        "acshower": "False",
        "acmlak": "False",
        "adultchangenote": null,
        "babychange": "True",
        "babycareroom": "False",
        "babychangenote": null,
        "dumppoint": "False",
        "dpwashout": "False",
        "dpafterhours": "False",
        "dumppointnote": null,
        "openinghours": "OPEN: Daylight hours",
        "openinghoursnote": null,
        "male": "False",
        "female": "False",
        "unisex": "True",
        "allgender": "False",
        "ambulant": "False",
        "accessible": "True",
        "lhtransfer": "False",
        "rhtransfer": "True",
        "toiletnote": null,
        "sharpsdisposal": "False",
        "drinkingwater": "False",
        "sanitarydisposal": "True",
        "menspaddisposal": "False",
        "shower": "False",
        "rank": 0.057308756,
        "geopoint": {
            "lon": 153.02014502,
            "lat": -27.46262703
        },
        "url_open_data_map": "https://data.brisbane.qld.gov.au/explore/dataset/public-toilets-in-brisbane/map/?q=facilityid:[65239]",
        "url": "https://toiletmap.gov.au/facility/65239",
        "lga_name": "Brisbane",
        "lga_code": "31000"
    }
]